dlordinal/__init__.py
dlordinal/datasets/__init__.py
dlordinal/datasets/adience.py
dlordinal/datasets/featuredataset.py
dlordinal/datasets/fgnet.py
dlordinal/datasets/hci.py
dlordinal/dropout/__init__.py
dlordinal/dropout/hybrid_dropout.py
dlordinal/losses/__init__.py
dlordinal/losses/beta_loss.py
dlordinal/losses/binomial_loss.py
dlordinal/losses/cdw.py
dlordinal/losses/corn_loss.py
dlordinal/losses/custom_targets_loss.py
dlordinal/losses/emd_loss.py
dlordinal/losses/exponential_loss.py
dlordinal/losses/general_triangular_loss.py
dlordinal/losses/geometric_loss.py
dlordinal/losses/mceloss.py
dlordinal/losses/mcewkloss.py
dlordinal/losses/ordinal_ecoc_distance_loss.py
dlordinal/losses/poisson_loss.py
dlordinal/losses/slace.py
dlordinal/losses/sord.py
dlordinal/losses/triangular_loss.py
dlordinal/losses/wkloss.py
dlordinal/metrics/__init__.py
dlordinal/metrics/metrics.py
dlordinal/output_layers/__init__.py
dlordinal/output_layers/clm.py
dlordinal/output_layers/copoc.py
dlordinal/output_layers/ordinal_fully_connected.py
dlordinal/output_layers/stick_breaking_layer.py
dlordinal/output_layers/utils.py
dlordinal/soft_labelling/__init__.py
dlordinal/soft_labelling/beta_distribution.py
dlordinal/soft_labelling/binomial_distribution.py
dlordinal/soft_labelling/exponential_distribution.py
dlordinal/soft_labelling/general_triangular_distribution.py
dlordinal/soft_labelling/geometric_distribution.py
dlordinal/soft_labelling/poisson_distribution.py
dlordinal/soft_labelling/triangular_distribution.py
dlordinal/soft_labelling/utils.py
dlordinal/wrappers/__init__.py
dlordinal/wrappers/corn.py
dlordinal/wrappers/obd_ecoc.py
dlordinal-2.6.0.dist-info/licenses/LICENSE
dlordinal-2.6.0.dist-info/METADATA
dlordinal-2.6.0.dist-info/WHEEL
dlordinal-2.6.0.dist-info/top_level.txt
dlordinal-2.6.0.dist-info/RECORD
