Metadata-Version: 2.4
Name: dlordinal
Version: 2.6.0
Summary: Deep learning for ordinal classification
Author-email: Francisco Bérchez-Moreno <fberchez@uco.es>, Víctor Manuel Vargas <vvargas@uco.es>, Javier Barbero-Gómez <jbarbero@uco.es>, Rafael Ayllón-Gavilán <rayllong@uco.es>, David Guijo-Rubio <dguijo@uco.es>
Project-URL: Source, https://github.com/ayrna/dlordinal
Project-URL: Documentation, https://dlordinal.readthedocs.io/en/latest/
Classifier: Programming Language :: Python :: 3
Classifier: License :: OSI Approved :: BSD License
Classifier: Operating System :: OS Independent
Classifier: Topic :: Scientific/Engineering :: Artificial Intelligence
Requires-Python: >=3.10
License-File: LICENSE
Requires-Dist: scikit-learn==1.*
Requires-Dist: numpy>=1.21
Requires-Dist: torch==2.*
Requires-Dist: torchvision>=0.13
Requires-Dist: pandas>=1
Requires-Dist: scipy>=1.7
Requires-Dist: scikit-image>=0.18
Requires-Dist: tqdm>=4
Requires-Dist: Pillow>=8
Requires-Dist: deprecated>=1.2
Provides-Extra: dev
Requires-Dist: pre-commit; extra == "dev"
Requires-Dist: pytest; extra == "dev"
Requires-Dist: pytest-cov; extra == "dev"
Requires-Dist: pytest-xdist[psutil]; extra == "dev"
Provides-Extra: docs
Requires-Dist: sphinx; extra == "docs"
Requires-Dist: sphinxcontrib-bibtex; extra == "docs"
Requires-Dist: sphinx-rtd-theme; extra == "docs"
Dynamic: license-file
